yt_concate/__init__.py
yt_concate/logs.py
yt_concate/main.py
yt_concate/setting.py
yt_concate/utils.py
yt_concate/model/__init__.py
yt_concate/model/found.py
yt_concate/model/yt.py
yt_concate/pipeline/__init__.py
yt_concate/pipeline/pipeline.py
yt_concate/pipeline/steps/__init__.py
yt_concate/pipeline/steps/downloads_captions.py
yt_concate/pipeline/steps/downloads_captions_by_multithreading.py
yt_concate/pipeline/steps/downloads_videos.py
yt_concate/pipeline/steps/downloads_videos_by_multithreading.py
yt_concate/pipeline/steps/edit_videos.py
yt_concate/pipeline/steps/get_video_list.py
yt_concate/pipeline/steps/initialize_yt.py
yt_concate/pipeline/steps/postflight.py
yt_concate/pipeline/steps/prefligjt.py
yt_concate/pipeline/steps/read_captions.py
yt_concate/pipeline/steps/search.py
yt_concate/pipeline/steps/step.py
Robert_Yt_Concate-0.1.1.dist-info/LICENSE.txt
Robert_Yt_Concate-0.1.1.dist-info/METADATA
Robert_Yt_Concate-0.1.1.dist-info/WHEEL
Robert_Yt_Concate-0.1.1.dist-info/top_level.txt
Robert_Yt_Concate-0.1.1.dist-info/RECORD
