Metadata-Version: 2.1
Name: Robert-Yt-Concate
Version: 0.1.1
Summary: Produce a concatenated video of clip that mentioned a word from youtube
Home-page: https://github.com/RobertChienShiba/Yt_Concate
Author: Robert Chien
Author-email: robertmadhead0919@gmail.com
License: MIT
Platform: UNKNOWN
Classifier: License :: OSI Approved :: MIT License
Classifier: Programming Language :: Python
Classifier: Programming Language :: Python :: 3
Classifier: Programming Language :: Python :: 3.6
Classifier: Programming Language :: Python :: Implementation :: CPython
Classifier: Programming Language :: Python :: Implementation :: PyPy
Requires-Python: >=3.8.5
Requires-Dist: moviepy
Requires-Dist: youtube-dl
Requires-Dist: requests
Requires-Dist: python-dotenv
Requires-Dist: urllib3
Requires-Dist: youtube-transcript-api
